Pro/SPI/src/spi_drive.v
module spi_drive (
        //系统接口
        input sys_clk,
        input rst_n,
        //用户接口
        input spi_start,
        input spi_end,
        input [7:0] data_send,
        output reg [7:0] data_rec,
        output reg send_done,
        output reg rec_done,
        //物理接口
        input spi_miso,
        output reg spi_csk,
        output reg spi_cs,
        output reg spi_mosi
    );
    parameter SYS_CLK_FREQ = 50_000_000;
    parameter SPI_CSK_FREQ = 1_000_000;//SPI时钟频率
    parameter SCK_CNT_MAX = SYS_CLK_FREQ/SPI_CSK_FREQ; //50
    parameter SCK_CNT_MAX_1_2 = SCK_CNT_MAX/2;

    reg [15:0] sck_cnt;   //spi时钟计数器
    reg [7:0]  send_cnt;  //发送数据计数器
    reg [7:0] data_send_r; //发送数据寄存器
    reg [7:0] data_rec_r; //接收数据寄存器
    reg spi_busy;//spi工作标志位

    //片选信号
    always @(posedge sys_clk ) begin
        if(!rst_n) begin
            spi_cs <=1'b1;
        end
        else if(spi_start) begin
            spi_cs <=1'b0;
        end
        else if(spi_end) begin
            spi_cs <=1'b1;
        end
        else
            spi_cs<=spi_cs;
    end

    //发送数据寄存
    always @(posedge sys_clk) begin
        if (!rst_n) begin
            data_send_r <= 8'h00;
        end
        else if(spi_start) begin
            data_send_r <= data_send;
        end
        else
            data_send_r <= data_send_r;
    end

    //spi时钟信号
    always @(posedge sys_clk ) begin
        if(!rst_n) begin
            spi_csk <= 1'b0;
        end
        else if(sck_cnt == (SCK_CNT_MAX_1_2-1) | sck_cnt== (SCK_CNT_MAX-1)) begin
            spi_csk <= ~spi_csk;
        end
        else
            spi_csk <= spi_csk;
    end

    //捕获spi开始和结束信号，更改状态标志位
    always @(posedge sys_clk ) begin
        if(!rst_n) begin
            spi_busy<=1'b0;
        end
        else if(spi_start) begin
            spi_busy<=1'b1;
        end
        else if(spi_end) begin
            spi_busy<=1'b0;
        end
        else
            spi_busy<=spi_busy;
    end

    //根据spi状态更新分频计数器和传输比特计数器
    always @(posedge sys_clk ) begin
        if(!rst_n) begin
            sck_cnt<=16'd0;
            send_cnt<=8'd0;
        end
        else if(spi_busy) begin
            if(sck_cnt==(SCK_CNT_MAX-1)) begin
                sck_cnt<=16'd0;
                send_cnt<=send_cnt+1'd1;
            end
            else begin
                sck_cnt<=sck_cnt+1'd1;
                send_cnt<=send_cnt;
            end

        end
        else begin
            sck_cnt<=16'd0;
            send_cnt<=8'd0;
        end
    end

    //mosi数据发送，产生发送完成标志位
    always @(posedge sys_clk ) begin
        if(!rst_n) begin
            spi_mosi<=1'd0;
            send_done<=1'd0;
        end
        else if(spi_busy) begin
            if(sck_cnt==16'd0) begin
                spi_mosi<=data_send_r[8'd7-send_cnt];
            end
            else begin
                spi_mosi<=spi_mosi;
            end
            if(send_cnt==8'd7 && sck_cnt==(SCK_CNT_MAX-1)) begin
                send_done<=1'd1;
            end
            else begin
                send_done<=1'd0;
            end
        end
        else begin
            spi_mosi<=1'd0;
            send_done<=1'd0;
        end

    end
    //miso数据接收，产生接收完成标志位
    always @(posedge sys_clk ) begin
        if(!rst_n) begin
            data_rec_r<=1'd0;
            rec_done<=1'd0;
        end
        else if(spi_busy) begin
            if(sck_cnt==(SCK_CNT_MAX_1_2-1)) begin
                data_rec_r[8'd7-send_cnt]<=spi_miso;
            end
            else begin
                data_rec_r[8'd7-send_cnt]<=data_rec_r[8'd7-send_cnt];
            end
            if(send_cnt==8'd7 && sck_cnt==(SCK_CNT_MAX-1)) begin
                rec_done<=1'd1;
                data_rec<=data_rec_r;
            end
            else begin
                rec_done<=1'd0;
            end
        end
        else begin
            rec_done<=1'd0;
            data_rec<=data_rec;
        end
    end
endmodule

Pro/SPI/src/spi_drive_tb.v
`timescale 1ns / 1ps

module spi_drive_tb();
    //initial begin
    //    $dumpfile("wave.vcd");        //生成的vcd文件名称
    //    $dumpvars(0, spi_drive_tb);    //tb模块名称
    //end
    // 定义输入输出信号，与被测试模块的端口对应
    reg sys_clk;
    reg rst_n;
    reg spi_start;
    reg spi_end;
    reg [7:0] data_send;
    wire [7:0] data_rec;
    wire send_done;
    wire rec_done;
    reg spi_miso;
    wire spi_csk;
    wire spi_cs;
    wire spi_mosi;

    // 实例化被测试的SPI驱动模块
    spi_drive uut (
                  .sys_clk(sys_clk),
                  .rst_n(rst_n),
                  .spi_start(spi_start),
                  .spi_end(spi_end),
                  .data_send(data_send),
                  .data_rec(data_rec),
                  .send_done(send_done),
                  .rec_done(rec_done),
                  .spi_miso(spi_miso),
                  .spi_csk(spi_csk),
                  .spi_cs(spi_cs),
                  .spi_mosi(spi_mosi)
              );

    // 产生时钟信号，频率可以根据实际需求调整，这里假设为50MHz
    always #10 sys_clk = ~sys_clk;

    initial begin
        // 初始化信号
        sys_clk = 1'b0;
        rst_n = 1'b0;
        spi_start = 1'b0;
        spi_end = 1'b0;
        data_send = 8'h00;
        spi_miso = 1'b0;

        // 复位信号有效一段时间，模拟复位操作
        #200 rst_n = 1'b1;

        // 开始一次SPI传输测试
        @(posedge sys_clk);
        spi_start = 1'b1;
        data_send = 8'hAA;  // 发送一个示例数据，可根据需要修改
        @(posedge sys_clk);
        spi_start = 1'b0;

        // 等待传输完成，通过检查发送完成和接收完成标志位
        wait(send_done && rec_done);

        // 结束SPI传输
        @(posedge sys_clk);
        spi_end = 1'b1;
        @(posedge sys_clk);
        spi_end = 1'b0;

        // 可以添加更多不同情况的SPI传输测试，比如发送不同的数据值、多次连续传输等

        // 结束仿真
        #200 $finish;
    end

    // 模拟MISO输入数据，这里简单设置为固定值，实际可根据需求改变逻辑
    always @(negedge spi_csk) begin
        if (spi_csk == 1'b0) begin
            spi_miso = ~spi_miso;  // 示例数据，可根据实际情况模拟不同的接收数据
        end
    end

endmodule

Pro/SPI/project/project.sim/sim_1/behav/xsim/wave.vcd
$date
   Sat Jan 11 20:00:50 2025
$end
$version
  2019.2
$end
$timescale
  1ps
$end
$scope module spi_drive_tb $end
$var reg 1 ! sys_clk $end
$var reg 1 " rst_n $end
$var reg 1 # spi_start $end
$var reg 1 $ spi_end $end
$var reg 8 % data_send [7:0] $end
$var wire 8 & data_rec [7:0] $end
$var wire 1 ' send_done $end
$var wire 1 ( rec_done $end
$var reg 1 ) spi_miso $end
$var wire 1 * spi_csk $end
$var wire 1 + spi_cs $end
$var wire 1 , spi_mosi $end
$scope module uut $end
$var wire 1 - sys_clk $end
$var wire 1 . rst_n $end
$var wire 1 / spi_start $end
$var wire 1 0 spi_end $end
$var wire 8 1 data_send [7:0] $end
$var reg 8 2 data_rec [7:0] $end
$var reg 1 3 send_done $end
$var reg 1 4 rec_done $end
$var wire 1 5 spi_miso $end
$var reg 1 6 spi_csk $end
$var reg 1 7 spi_cs $end
$var reg 1 8 spi_mosi $end
$var reg 16 9 sck_cnt [15:0] $end
$var reg 8 : send_cnt [7:0] $end
$var reg 8 ; data_send_r [7:0] $end
$var reg 8 < data_rec_r [7:0] $end
$var reg 1 = spi_busy $end
$var parameter 32 > SYS_CLK_FREQ [31:0] $end
$var parameter 32 ? SPI_CSK_FREQ [31:0] $end
$var parameter 32 @ SCK_CNT_MAX [31:0] $end
$var parameter 32 A SCK_CNT_MAX_1_2 [31:0] $end
$upscope $end
$upscope $end
$enddefinitions $end
#0
$dumpvars
0!
0"
0#
0$
b0 %
bx &
x'
x(
0)
x*
x+
x,
0-
0.
0/
00
b0 1
bx 2
x3
x4
05
x6
x7
x8
bx 9
bx :
bx ;
bx <
x=
b10111110101111000010000000 >
b11110100001001000000 ?
b110010 @
b11001 A
$end
#10000
1!
0'
0(
1)
0*
1+
0,
1-
03
04
15
06
17
08
b0 9
b0 :
b0 ;
b0 <
0=
#20000
0!
0-
#30000
1!
1-
#40000
0!
0-
#50000
1!
1-
#60000
0!
0-
#70000
1!
1-
#80000
0!
0-
#90000
1!
1-
#100000
0!
0-
#110000
1!
1-
#120000
0!
0-
#130000
1!
1-
#140000
0!
0-
#150000
1!
1-
#160000
0!
0-
#170000
1!
1-
#180000
0!
0-
#190000
1!
1-
#200000
0!
1"
0-
1.
#210000
1!
1#
b10101010 %
0+
1-
1/
b10101010 1
07
b10101010 ;
1=
#220000
0!
0-
#230000
1!
0#
1,
1-
0/
18
b1 9
#240000
0!
0-
#250000
1!
1-
b10 9
#260000
0!
0-
#270000
1!
1-
b11 9
#280000
0!
0-
#290000
1!
1-
b100 9
#300000
0!
0-
#310000
1!
1-
b101 9
#320000
0!
0-
#330000
1!
1-
b110 9
#340000
0!
0-
#350000
1!
1-
b111 9
#360000
0!
0-
#370000
1!
1-
b1000 9
#380000
0!
0-
#390000
1!
1-
b1001 9
#400000
0!
0-
#410000
1!
1-
b1010 9
#420000
0!
0-
#430000
1!
1-
b1011 9
#440000
0!
0-
#450000
1!
1-
b1100 9
#460000
0!
0-
#470000
1!
1-
b1101 9
#480000
0!
0-
#490000
1!
1-
b1110 9
#500000
0!
0-
#510000
1!
1-
b1111 9
#520000
0!
0-
#530000
1!
1-
b10000 9
#540000
0!
0-
#550000
1!
1-
b10001 9
#560000
0!
0-
#570000
1!
1-
b10010 9
#580000
0!
0-
#590000
1!
1-
b10011 9
#600000
0!
0-
#610000
1!
1-
b10100 9
#620000
0!
0-
#630000
1!
1-
b10101 9
#640000
0!
0-
#650000
1!
1-
b10110 9
#660000
0!
0-
#670000
1!
1-
b10111 9
#680000
0!
0-
#690000
1!
1-
b11000 9
#700000
0!
0-
#710000
1!
1*
1-
16
b11001 9
b10000000 <
#720000
0!
0-
#730000
1!
1-
b11010 9
#740000
0!
0-
#750000
1!
1-
b11011 9
#760000
0!
0-
#770000
1!
1-
b11100 9
#780000
0!
0-
#790000
1!
1-
b11101 9
#800000
0!
0-
#810000
1!
1-
b11110 9
#820000
0!
0-
#830000
1!
1-
b11111 9
#840000
0!
0-
#850000
1!
1-
b100000 9
#860000
0!
0-
#870000
1!
1-
b100001 9
#880000
0!
0-
#890000
1!
1-
b100010 9
#900000
0!
0-
#910000
1!
1-
b100011 9
#920000
0!
0-
#930000
1!
1-
b100100 9
#940000
0!
0-
#950000
1!
1-
b100101 9
#960000
0!
0-
#970000
1!
1-
b100110 9
#980000
0!
0-
#990000
1!
1-
b100111 9
#1000000
0!
0-
#1010000
1!
1-
b101000 9
#1020000
0!
0-
#1030000
1!
1-
b101001 9
#1040000
0!
0-
#1050000
1!
1-
b101010 9
#1060000
0!
0-
#1070000
1!
1-
b101011 9
#1080000
0!
0-
#1090000
1!
1-
b101100 9
#1100000
0!
0-
#1110000
1!
1-
b101101 9
#1120000
0!
0-
#1130000
1!
1-
b101110 9
#1140000
0!
0-
#1150000
1!
1-
b101111 9
#1160000
0!
0-
#1170000
1!
1-
b110000 9
#1180000
0!
0-
#1190000
1!
1-
b110001 9
#1200000
0!
0-
#1210000
1!
0)
0*
1-
05
06
b0 9
b1 :
#1220000
0!
0-
#1230000
1!
0,
1-
08
b1 9
#1240000
0!
0-
#1250000
1!
1-
b10 9
#1260000
0!
0-
#1270000
1!
1-
b11 9
#1280000
0!
0-
#1290000
1!
1-
b100 9
#1300000
0!
0-
#1310000
1!
1-
b101 9
#1320000
0!
0-
#1330000
1!
1-
b110 9
#1340000
0!
0-
#1350000
1!
1-
b111 9
#1360000
0!
0-
#1370000
1!
1-
b1000 9
#1380000
0!
0-
#1390000
1!
1-
b1001 9
#1400000
0!
0-
#1410000
1!
1-
b1010 9
#1420000
0!
0-
#1430000
1!
1-
b1011 9
#1440000
0!
0-
#1450000
1!
1-
b1100 9
#1460000
0!
0-
#1470000
1!
1-
b1101 9
#1480000
0!
0-
#1490000
1!
1-
b1110 9
#1500000
0!
0-
#1510000
1!
1-
b1111 9
#1520000
0!
0-
#1530000
1!
1-
b10000 9
#1540000
0!
0-
#1550000
1!
1-
b10001 9
#1560000
0!
0-
#1570000
1!
1-
b10010 9
#1580000
0!
0-
#1590000
1!
1-
b10011 9
#1600000
0!
0-
#1610000
1!
1-
b10100 9
#1620000
0!
0-
#1630000
1!
1-
b10101 9
#1640000
0!
0-
#1650000
1!
1-
b10110 9
#1660000
0!
0-
#1670000
1!
1-
b10111 9
#1680000
0!
0-
#1690000
1!
1-
b11000 9
#1700000
0!
0-
#1710000
1!
1*
1-
16
b11001 9
#1720000
0!
0-
#1730000
1!
1-
b11010 9
#1740000
0!
0-
#1750000
1!
1-
b11011 9
#1760000
0!
0-
#1770000
1!
1-
b11100 9
#1780000
0!
0-
#1790000
1!
1-
b11101 9
#1800000
0!
0-
#1810000
1!
1-
b11110 9
#1820000
0!
0-
#1830000
1!
1-
b11111 9
#1840000
0!
0-
#1850000
1!
1-
b100000 9
#1860000
0!
0-
#1870000
1!
1-
b100001 9
#1880000
0!
0-
#1890000
1!
1-
b100010 9
#1900000
0!
0-
#1910000
1!
1-
b100011 9
#1920000
0!
0-
#1930000
1!
1-
b100100 9
#1940000
0!
0-
#1950000
1!
1-
b100101 9
#1960000
0!
0-
#1970000
1!
1-
b100110 9
#1980000
0!
0-
#1990000
1!
1-
b100111 9
#2000000
0!
0-
#2010000
1!
1-
b101000 9
#2020000
0!
0-
#2030000
1!
1-
b101001 9
#2040000
0!
0-
#2050000
1!
1-
b101010 9
#2060000
0!
0-
#2070000
1!
1-
b101011 9
#2080000
0!
0-
#2090000
1!
1-
b101100 9
#2100000
0!
0-
#2110000
1!
1-
b101101 9
#2120000
0!
0-
#2130000
1!
1-
b101110 9
#2140000
0!
0-
#2150000
1!
1-
b101111 9
#2160000
0!
0-
#2170000
1!
1-
b110000 9
#2180000
0!
0-
#2190000
1!
1-
b110001 9
#2200000
0!
0-
#2210000
1!
1)
0*
1-
15
06
b0 9
b10 :
#2220000
0!
0-
#2230000
1!
1,
1-
18
b1 9
#2240000
0!
0-
#2250000
1!
1-
b10 9
#2260000
0!
0-
#2270000
1!
1-
b11 9
#2280000
0!
0-
#2290000
1!
1-
b100 9
#2300000
0!
0-
#2310000
1!
1-
b101 9
#2320000
0!
0-
#2330000
1!
1-
b110 9
#2340000
0!
0-
#2350000
1!
1-
b111 9
#2360000
0!
0-
#2370000
1!
1-
b1000 9
#2380000
0!
0-
#2390000
1!
1-
b1001 9
#2400000
0!
0-
#2410000
1!
1-
b1010 9
#2420000
0!
0-
#2430000
1!
1-
b1011 9
#2440000
0!
0-
#2450000
1!
1-
b1100 9
#2460000
0!
0-
#2470000
1!
1-
b1101 9
#2480000
0!
0-
#2490000
1!
1-
b1110 9
#2500000
0!
0-
#2510000
1!
1-
b1111 9
#2520000
0!
0-
#2530000
1!
1-
b10000 9
#2540000
0!
0-
#2550000
1!
1-
b10001 9
#2560000
0!
0-
#2570000
1!
1-
b10010 9
#2580000
0!
0-
#2590000
1!
1-
b10011 9
#2600000
0!
0-
#2610000
1!
1-
b10100 9
#2620000
0!
0-
#2630000
1!
1-
b10101 9
#2640000
0!
0-
#2650000
1!
1-
b10110 9
#2660000
0!
0-
#2670000
1!
1-
b10111 9
#2680000
0!
0-
#2690000
1!
1-
b11000 9
#2700000
0!
0-
#2710000
1!
1*
1-
16
b11001 9
b10100000 <
#2720000
0!
0-
#2730000
1!
1-
b11010 9
#2740000
0!
0-
#2750000
1!
1-
b11011 9
#2760000
0!
0-
#2770000
1!
1-
b11100 9
#2780000
0!
0-
#2790000
1!
1-
b11101 9
#2800000
0!
0-
#2810000
1!
1-
b11110 9
#2820000
0!
0-
#2830000
1!
1-
b11111 9
#2840000
0!
0-
#2850000
1!
1-
b100000 9
#2860000
0!
0-
#2870000
1!
1-
b100001 9
#2880000
0!
0-
#2890000
1!
1-
b100010 9
#2900000
0!
0-
#2910000
1!
1-
b100011 9
#2920000
0!
0-
#2930000
1!
1-
b100100 9
#2940000
0!
0-
#2950000
1!
1-
b100101 9
#2960000
0!
0-
#2970000
1!
1-
b100110 9
#2980000
0!
0-
#2990000
1!
1-
b100111 9
#3000000
0!
0-
#3010000
1!
1-
b101000 9
#3020000
0!
0-
#3030000
1!
1-
b101001 9
#3040000
0!
0-
#3050000
1!
1-
b101010 9
#3060000
0!
0-
#3070000
1!
1-
b101011 9
#3080000
0!
0-
#3090000
1!
1-
b101100 9
#3100000
0!
0-
#3110000
1!
1-
b101101 9
#3120000
0!
0-
#3130000
1!
1-
b101110 9
#3140000
0!
0-
#3150000
1!
1-
b101111 9
#3160000
0!
0-
#3170000
1!
1-
b110000 9
#3180000
0!
0-
#3190000
1!
1-
b110001 9
#3200000
0!
0-
#3210000
1!
0)
0*
1-
05
06
b0 9
b11 :
#3220000
0!
0-
#3230000
1!
0,
1-
08
b1 9
#3240000
0!
0-
#3250000
1!
1-
b10 9
#3260000
0!
0-
#3270000
1!
1-
b11 9
#3280000
0!
0-
#3290000
1!
1-
b100 9
#3300000
0!
0-
#3310000
1!
1-
b101 9
#3320000
0!
0-
#3330000
1!
1-
b110 9
#3340000
0!
0-
#3350000
1!
1-
b111 9
#3360000
0!
0-
#3370000
1!
1-
b1000 9
#3380000
0!
0-
#3390000
1!
1-
b1001 9
#3400000
0!
0-
#3410000
1!
1-
b1010 9
#3420000
0!
0-
#3430000
1!
1-
b1011 9
#3440000
0!
0-
#3450000
1!
1-
b1100 9
#3460000
0!
0-
#3470000
1!
1-
b1101 9
#3480000
0!
0-
#3490000
1!
1-
b1110 9
#3500000
0!
0-
#3510000
1!
1-
b1111 9
#3520000
0!
0-
#3530000
1!
1-
b10000 9
#3540000
0!
0-
#3550000
1!
1-
b10001 9
#3560000
0!
0-
#3570000
1!
1-
b10010 9
#3580000
0!
0-
#3590000
1!
1-
b10011 9
#3600000
0!
0-
#3610000
1!
1-
b10100 9
#3620000
0!
0-
#3630000
1!
1-
b10101 9
#3640000
0!
0-
#3650000
1!
1-
b10110 9
#3660000
0!
0-
#3670000
1!
1-
b10111 9
#3680000
0!
0-
#3690000
1!
1-
b11000 9
#3700000
0!
0-
#3710000
1!
1*
1-
16
b11001 9
#3720000
0!
0-
#3730000
1!
1-
b11010 9
#3740000
0!
0-
#3750000
1!
1-
b11011 9
#3760000
0!
0-
#3770000
1!
1-
b11100 9
#3780000
0!
0-
#3790000
1!
1-
b11101 9
#3800000
0!
0-
#3810000
1!
1-
b11110 9
#3820000
0!
0-
#3830000
1!
1-
b11111 9
#3840000
0!
0-
#3850000
1!
1-
b100000 9
#3860000
0!
0-
#3870000
1!
1-
b100001 9
#3880000
0!
0-
#3890000
1!
1-
b100010 9
#3900000
0!
0-
#3910000
1!
1-
b100011 9
#3920000
0!
0-
#3930000
1!
1-
b100100 9
#3940000
0!
0-
#3950000
1!
1-
b100101 9
#3960000
0!
0-
#3970000
1!
1-
b100110 9
#3980000
0!
0-
#3990000
1!
1-
b100111 9
#4000000
0!
0-
#4010000
1!
1-
b101000 9
#4020000
0!
0-
#4030000
1!
1-
b101001 9
#4040000
0!
0-
#4050000
1!
1-
b101010 9
#4060000
0!
0-
#4070000
1!
1-
b101011 9
#4080000
0!
0-
#4090000
1!
1-
b101100 9
#4100000
0!
0-
#4110000
1!
1-
b101101 9
#4120000
0!
0-
#4130000
1!
1-
b101110 9
#4140000
0!
0-
#4150000
1!
1-
b101111 9
#4160000
0!
0-
#4170000
1!
1-
b110000 9
#4180000
0!
0-
#4190000
1!
1-
b110001 9
#4200000
0!
0-
#4210000
1!
1)
0*
1-
15
06
b0 9
b100 :
#4220000
0!
0-
#4230000
1!
1,
1-
18
b1 9
#4240000
0!
0-
#4250000
1!
1-
b10 9
#4260000
0!
0-
#4270000
1!
1-
b11 9
#4280000
0!
0-
#4290000
1!
1-
b100 9
#4300000
0!
0-
#4310000
1!
1-
b101 9
#4320000
0!
0-
#4330000
1!
1-
b110 9
#4340000
0!
0-
#4350000
1!
1-
b111 9
#4360000
0!
0-
#4370000
1!
1-
b1000 9
#4380000
0!
0-
#4390000
1!
1-
b1001 9
#4400000
0!
0-
#4410000
1!
1-
b1010 9
#4420000
0!
0-
#4430000
1!
1-
b1011 9
#4440000
0!
0-
#4450000
1!
1-
b1100 9
#4460000
0!
0-
#4470000
1!
1-
b1101 9
#4480000
0!
0-
#4490000
1!
1-
b1110 9
#4500000
0!
0-
#4510000
1!
1-
b1111 9
#4520000
0!
0-
#4530000
1!
1-
b10000 9
#4540000
0!
0-
#4550000
1!
1-
b10001 9
#4560000
0!
0-
#4570000
1!
1-
b10010 9
#4580000
0!
0-
#4590000
1!
1-
b10011 9
#4600000
0!
0-
#4610000
1!
1-
b10100 9
#4620000
0!
0-
#4630000
1!
1-
b10101 9
#4640000
0!
0-
#4650000
1!
1-
b10110 9
#4660000
0!
0-
#4670000
1!
1-
b10111 9
#4680000
0!
0-
#4690000
1!
1-
b11000 9
#4700000
0!
0-
#4710000
1!
1*
1-
16
b11001 9
b10101000 <
#4720000
0!
0-
#4730000
1!
1-
b11010 9
#4740000
0!
0-
#4750000
1!
1-
b11011 9
#4760000
0!
0-
#4770000
1!
1-
b11100 9
#4780000
0!
0-
#4790000
1!
1-
b11101 9
#4800000
0!
0-
#4810000
1!
1-
b11110 9
#4820000
0!
0-
#4830000
1!
1-
b11111 9
#4840000
0!
0-
#4850000
1!
1-
b100000 9
#4860000
0!
0-
#4870000
1!
1-
b100001 9
#4880000
0!
0-
#4890000
1!
1-
b100010 9
#4900000
0!
0-
#4910000
1!
1-
b100011 9
#4920000
0!
0-
#4930000
1!
1-
b100100 9
#4940000
0!
0-
#4950000
1!
1-
b100101 9
#4960000
0!
0-
#4970000
1!
1-
b100110 9
#4980000
0!
0-
#4990000
1!
1-
b100111 9
#5000000
0!
0-
#5010000
1!
1-
b101000 9
#5020000
0!
0-
#5030000
1!
1-
b101001 9
#5040000
0!
0-
#5050000
1!
1-
b101010 9
#5060000
0!
0-
#5070000
1!
1-
b101011 9
#5080000
0!
0-
#5090000
1!
1-
b101100 9
#5100000
0!
0-
#5110000
1!
1-
b101101 9
#5120000
0!
0-
#5130000
1!
1-
b101110 9
#5140000
0!
0-
#5150000
1!
1-
b101111 9
#5160000
0!
0-
#5170000
1!
1-
b110000 9
#5180000
0!
0-
#5190000
1!
1-
b110001 9
#5200000
0!
0-
#5210000
1!
0)
0*
1-
05
06
b0 9
b101 :
#5220000
0!
0-
#5230000
1!
0,
1-
08
b1 9
#5240000
0!
0-
#5250000
1!
1-
b10 9
#5260000
0!
0-
#5270000
1!
1-
b11 9
#5280000
0!
0-
#5290000
1!
1-
b100 9
#5300000
0!
0-
#5310000
1!
1-
b101 9
#5320000
0!
0-
#5330000
1!
1-
b110 9
#5340000
0!
0-
#5350000
1!
1-
b111 9
#5360000
0!
0-
#5370000
1!
1-
b1000 9
#5380000
0!
0-
#5390000
1!
1-
b1001 9
#5400000
0!
0-
#5410000
1!
1-
b1010 9
#5420000
0!
0-
#5430000
1!
1-
b1011 9
#5440000
0!
0-
#5450000
1!
1-
b1100 9
#5460000
0!
0-
#5470000
1!
1-
b1101 9
#5480000
0!
0-
#5490000
1!
1-
b1110 9
#5500000
0!
0-
#5510000
1!
1-
b1111 9
#5520000
0!
0-
#5530000
1!
1-
b10000 9
#5540000
0!
0-
#5550000
1!
1-
b10001 9
#5560000
0!
0-
#5570000
1!
1-
b10010 9
#5580000
0!
0-
#5590000
1!
1-
b10011 9
#5600000
0!
0-
#5610000
1!
1-
b10100 9
#5620000
0!
0-
#5630000
1!
1-
b10101 9
#5640000
0!
0-
#5650000
1!
1-
b10110 9
#5660000
0!
0-
#5670000
1!
1-
b10111 9
#5680000
0!
0-
#5690000
1!
1-
b11000 9
#5700000
0!
0-
#5710000
1!
1*
1-
16
b11001 9
#5720000
0!
0-
#5730000
1!
1-
b11010 9
#5740000
0!
0-
#5750000
1!
1-
b11011 9
#5760000
0!
0-
#5770000
1!
1-
b11100 9
#5780000
0!
0-
#5790000
1!
1-
b11101 9
#5800000
0!
0-
#5810000
1!
1-
b11110 9
#5820000
0!
0-
#5830000
1!
1-
b11111 9
#5840000
0!
0-
#5850000
1!
1-
b100000 9
#5860000
0!
0-
#5870000
1!
1-
b100001 9
#5880000
0!
0-
#5890000
1!
1-
b100010 9
#5900000
0!
0-
#5910000
1!
1-
b100011 9
#5920000
0!
0-
#5930000
1!
1-
b100100 9
#5940000
0!
0-
#5950000
1!
1-
b100101 9
#5960000
0!
0-
#5970000
1!
1-
b100110 9
#5980000
0!
0-
#5990000
1!
1-
b100111 9
#6000000
0!
0-
#6010000
1!
1-
b101000 9
#6020000
0!
0-
#6030000
1!
1-
b101001 9
#6040000
0!
0-
#6050000
1!
1-
b101010 9
#6060000
0!
0-
#6070000
1!
1-
b101011 9
#6080000
0!
0-
#6090000
1!
1-
b101100 9
#6100000
0!
0-
#6110000
1!
1-
b101101 9
#6120000
0!
0-
#6130000
1!
1-
b101110 9
#6140000
0!
0-
#6150000
1!
1-
b101111 9
#6160000
0!
0-
#6170000
1!
1-
b110000 9
#6180000
0!
0-
#6190000
1!
1-
b110001 9
#6200000
0!
0-
#6210000
1!
1)
0*
1-
15
06
b0 9
b110 :
#6220000
0!
0-
#6230000
1!
1,
1-
18
b1 9
#6240000
0!
0-
#6250000
1!
1-
b10 9
#6260000
0!
0-
#6270000
1!
1-
b11 9
#6280000
0!
0-
#6290000
1!
1-
b100 9
#6300000
0!
0-
#6310000
1!
1-
b101 9
#6320000
0!
0-
#6330000
1!
1-
b110 9
#6340000
0!
0-
#6350000
1!
1-
b111 9
#6360000
0!
0-
#6370000
1!
1-
b1000 9
#6380000
0!
0-
#6390000
1!
1-
b1001 9
#6400000
0!
0-
#6410000
1!
1-
b1010 9
#6420000
0!
0-
#6430000
1!
1-
b1011 9
#6440000
0!
0-
#6450000
1!
1-
b1100 9
#6460000
0!
0-
#6470000
1!
1-
b1101 9
#6480000
0!
0-
#6490000
1!
1-
b1110 9
#6500000
0!
0-
#6510000
1!
1-
b1111 9
#6520000
0!
0-
#6530000
1!
1-
b10000 9
#6540000
0!
0-
#6550000
1!
1-
b10001 9
#6560000
0!
0-
#6570000
1!
1-
b10010 9
#6580000
0!
0-
#6590000
1!
1-
b10011 9
#6600000
0!
0-
#6610000
1!
1-
b10100 9
#6620000
0!
0-
#6630000
1!
1-
b10101 9
#6640000
0!
0-
#6650000
1!
1-
b10110 9
#6660000
0!
0-
#6670000
1!
1-
b10111 9
#6680000
0!
0-
#6690000
1!
1-
b11000 9
#6700000
0!
0-
#6710000
1!
1*
1-
16
b11001 9
b10101010 <
#6720000
0!
0-
#6730000
1!
1-
b11010 9
#6740000
0!
0-
#6750000
1!
1-
b11011 9
#6760000
0!
0-
#6770000
1!
1-
b11100 9
#6780000
0!
0-
#6790000
1!
1-
b11101 9
#6800000
0!
0-
#6810000
1!
1-
b11110 9
#6820000
0!
0-
#6830000
1!
1-
b11111 9
#6840000
0!
0-
#6850000
1!
1-
b100000 9
#6860000
0!
0-
#6870000
1!
1-
b100001 9
#6880000
0!
0-
#6890000
1!
1-
b100010 9
#6900000
0!
0-
#6910000
1!
1-
b100011 9
#6920000
0!
0-
#6930000
1!
1-
b100100 9
#6940000
0!
0-
#6950000
1!
1-
b100101 9
#6960000
0!
0-
#6970000
1!
1-
b100110 9
#6980000
0!
0-
#6990000
1!
1-
b100111 9
#7000000
0!
0-
#7010000
1!
1-
b101000 9
#7020000
0!
0-
#7030000
1!
1-
b101001 9
#7040000
0!
0-
#7050000
1!
1-
b101010 9
#7060000
0!
0-
#7070000
1!
1-
b101011 9
#7080000
0!
0-
#7090000
1!
1-
b101100 9
#7100000
0!
0-
#7110000
1!
1-
b101101 9
#7120000
0!
0-
#7130000
1!
1-
b101110 9
#7140000
0!
0-
#7150000
1!
1-
b101111 9
#7160000
0!
0-
#7170000
1!
1-
b110000 9
#7180000
0!
0-
#7190000
1!
1-
b110001 9
#7200000
0!
0-
#7210000
1!
0)
0*
1-
05
06
b0 9
b111 :
#7220000
0!
0-
#7230000
1!
0,
1-
08
b1 9
#7240000
0!
0-
#7250000
1!
1-
b10 9
#7260000
0!
0-
#7270000
1!
1-
b11 9
#7280000
0!
0-
#7290000
1!
1-
b100 9
#7300000
0!
0-
#7310000
1!
1-
b101 9
#7320000
0!
0-
#7330000
1!
1-
b110 9
#7340000
0!
0-
#7350000
1!
1-
b111 9
#7360000
0!
0-
#7370000
1!
1-
b1000 9
#7380000
0!
0-
#7390000
1!
1-
b1001 9
#7400000
0!
0-
#7410000
1!
1-
b1010 9
#7420000
0!
0-
#7430000
1!
1-
b1011 9
#7440000
0!
0-
#7450000
1!
1-
b1100 9
#7460000
0!
0-
#7470000
1!
1-
b1101 9
#7480000
0!
0-
#7490000
1!
1-
b1110 9
#7500000
0!
0-
#7510000
1!
1-
b1111 9
#7520000
0!
0-
#7530000
1!
1-
b10000 9
#7540000
0!
0-
#7550000
1!
1-
b10001 9
#7560000
0!
0-
#7570000
1!
1-
b10010 9
#7580000
0!
0-
#7590000
1!
1-
b10011 9
#7600000
0!
0-
#7610000
1!
1-
b10100 9
#7620000
0!
0-
#7630000
1!
1-
b10101 9
#7640000
0!
0-
#7650000
1!
1-
b10110 9
#7660000
0!
0-
#7670000
1!
1-
b10111 9
#7680000
0!
0-
#7690000
1!
1-
b11000 9
#7700000
0!
0-
#7710000
1!
1*
1-
16
b11001 9
#7720000
0!
0-
#7730000
1!
1-
b11010 9
#7740000
0!
0-
#7750000
1!
1-
b11011 9
#7760000
0!
0-
#7770000
1!
1-
b11100 9
#7780000
0!
0-
#7790000
1!
1-
b11101 9
#7800000
0!
0-
#7810000
1!
1-
b11110 9
#7820000
0!
0-
#7830000
1!
1-
b11111 9
#7840000
0!
0-
#7850000
1!
1-
b100000 9
#7860000
0!
0-
#7870000
1!
1-
b100001 9
#7880000
0!
0-
#7890000
1!
1-
b100010 9
#7900000
0!
0-
#7910000
1!
1-
b100011 9
#7920000
0!
0-
#7930000
1!
1-
b100100 9
